[
    {
        "id": 0,
        "title": "Basic Page",
        "items": [
            {
                "id": 0,
                "itemTitle": "Basic Page",
                "itemsList": [
                    {
                        "id": 0,
                        "itemsListTitle": "Basic Page"
                    },
                    {
                        "id": 1,
                        "itemsListTitle": "Drawing"
                    },
                    {
                        "id": 2,
                        "itemsListTitle": "Image Gallery"
                    }
                ]
            },
            {
                "id": 1,
                "itemTitle": "Drawing",
                "itemsList": [
                    {
                        "id": 0,
                        "itemsListTitle": "Basic Page"
                    },
                    {
                        "id": 1,
                        "itemsListTitle": "Drawing"
                    },
                    {
                        "id": 2,
                        "itemsListTitle": "Image Gallery"
                    }
                ]
            },
            {
                "id": 2,
                "itemTitle": "Image Gallery",
                "itemsList": [
                    {
                        "id": 0,
                        "itemsListTitle": "Basic Page"
                    },
                    {
                        "id": 1,
                        "itemsListTitle": "Drawing"
                    },
                    {
                        "id": 2,
                        "itemsListTitle": "Image Gallery"
                    }
                ]
            }
        ]
    },
    {
        "id": 1,
        "title": "Basic Page 2",
        "items": [
            {
                "id": 0,
                "itemTitle": "Basic Page",
                "itemsList": [
                    {
                        "id": 0,
                        "itemsListTitle": "Basic Page"
                    },
                    {
                        "id": 1,
                        "itemsListTitle": "Drawing"
                    },
                    {
                        "id": 2,
                        "itemsListTitle": "Image Gallery"
                    }
                ]
            },
            {
                "id": 1,
                "itemTitle": "Drawing",
                "itemsList": [
                    {
                        "id": 0,
                        "itemsListTitle": "Basic Page"
                    },
                    {
                        "id": 1,
                        "itemsListTitle": "Drawing"
                    },
                    {
                        "id": 2,
                        "itemsListTitle": "Image Gallery"
                    }
                ]
            },
            {
                "id": 2,
                "itemTitle": "Image Gallery",
                "itemsList": [
                    {
                        "id": 0,
                        "itemsListTitle": "Basic Page"
                    },
                    {
                        "id": 1,
                        "itemsListTitle": "Drawing"
                    },
                    {
                        "id": 2,
                        "itemsListTitle": "Image Gallery"
                    }
                ]
            }
        ]
    },
    {
        "id": 2,
        "title": "Basic Page 3",
        "items": [
            {
                "id": 0,
                "itemTitle": "Basic Page",
                "itemsList": [
                    {
                        "id": 0,
                        "itemsListTitle": "Basic Page"
                    },
                    {
                        "id": 1,
                        "itemsListTitle": "Drawing"
                    },
                    {
                        "id": 2,
                        "itemsListTitle": "Image Gallery"
                    }
                ]
            },
            {
                "id": 1,
                "itemTitle": "Drawing",
                "itemsList": [
                    {
                        "id": 0,
                        "itemsListTitle": "Basic Page"
                    },
                    {
                        "id": 1,
                        "itemsListTitle": "Drawing"
                    },
                    {
                        "id": 2,
                        "itemsListTitle": "Image Gallery"
                    }
                ]
            },
            {
                "id": 2,
                "itemTitle": "Image Gallery",
                "itemsList": [
                    {
                        "id": 0,
                        "itemsListTitle": "Basic Page"
                    },
                    {
                        "id": 1,
                        "itemsListTitle": "Drawing"
                    },
                    {
                        "id": 2,
                        "itemsListTitle": "Image Gallery"
                    }
                ]
            }
        ]
    }
]